{
  "schema_version": "parity_expected_v1",
  "tolerances": {
    "default": {"abs": 1e-06, "rel": 1e-06},
    "metrics": {
      "engines.direct_cpu.summary.mean_lux": {"abs": 1.0, "rel": 0.03},
      "engines.direct_cpu.summary.min_lux": {"abs": 1.0, "rel": 0.05},
      "engines.direct_cpu.summary.max_lux": {"abs": 1.5, "rel": 0.03},
      "engines.direct_cpu.summary.uniformity_ratio": {"abs": 0.03, "rel": 0.06}
    }
  },
  "ignore": [],
  "expected": {
    "pack_name": "L_room_diffuse",
    "engines": {
      "direct_cpu": {
        "job_type": "direct",
        "summary": {
          "mean_lux": 77.93538526031399,
          "min_lux": 21.90735351048493,
          "max_lux": 198.81810769460674,
          "uniformity_ratio": 0.28109636511466024
        }
      },
      "radiosity_cpu": {
        "job_type": "radiosity",
        "summary": {}
      }
    }
  }
}
